PyRegressionTesting/CommandLine.py
PyRegressionTesting/TestRunner.py
PyRegressionTesting/ThreadWithReturnValue.py
PyRegressionTesting/__init__.py
PyRegressionTesting/TestModule/AssertModule.py
PyRegressionTesting/TestModule/ClickModule.py
PyRegressionTesting/TestModule/EmailModule.py
PyRegressionTesting/TestModule/HoverModule.py
PyRegressionTesting/TestModule/InputModule.py
PyRegressionTesting/TestModule/SetStorageModule.py
PyRegressionTesting/TestModule/WaitModule.py
PyRegressionTesting/TestModule/__init__.py
PyRegressionTesting/Utils/Constants.py
PyRegressionTesting/Utils/Helper.py
PyRegressionTesting/Utils/Logger.py
PyRegressionTesting/Utils/RunnerResult.py
PyRegressionTesting/Utils/TestModuleResult.py
PyRegressionTesting/Utils/__init__.py
PyRegressionTesting/Utils/Config/MailConfig.py
PyRegressionTesting/Utils/Config/TestsConfig.py
PyRegressionTesting/Utils/Config/__init__.py
PyRegressionTesting-0.1b23.dist-info/METADATA
PyRegressionTesting-0.1b23.dist-info/WHEEL
PyRegressionTesting-0.1b23.dist-info/entry_points.txt
PyRegressionTesting-0.1b23.dist-info/top_level.txt
PyRegressionTesting-0.1b23.dist-info/RECORD
