Metadata-Version: 2.1
Name: PyRegressionTesting
Version: 0.1b23
Summary: Easily run regression tests on your website!
Home-page: https://github.com/saschahuber/PyRegressionTesting
Author: Sascha Huber
Author-email: kontakt@sascha-huber.com
License: UNKNOWN
Platform: UNKNOWN
Classifier: Programming Language :: Python :: 3.6
Classifier: License :: OSI Approved :: MIT License
Classifier: Operating System :: OS Independent
Requires-Dist: selenium
